{
  "kind": "collectionType",
  "collectionName": "rental_vehicles",
  "info": {
    "singularName": "rental-vehicle",
    "pluralName": "rental-vehicles",
    "displayName": "Rental Vehicle"
  },
  "options": {
    "draftAndPublish": true
  },
  "pluginOptions": {
    "i18n": {
      "localized": true
    }
  },
  "attributes": {
    "vehicleId": {
      "type": "string",
      "pluginOptions": {
        "i18n": {
          "localized": false
        }
      }
    },
    "model": {
      "type": "string",
      "pluginOptions": {
        "i18n": {
          "localized": false
        }
      }
    },
    "price": {
      "type": "string",
      "pluginOptions": {
        "i18n": {
          "localized": true
        }
      }
    },
    "image": {
      "type": "media",
      "multiple": false,
      "required": false,
      "allowedTypes": [
        "images"
      ],
      "pluginOptions": {
        "i18n": {
          "localized": false
        }
      }
    },
    "title": {
      "type": "string",
      "pluginOptions": {
        "i18n": {
          "localized": true
        }
      }
    },
    "description": {
      "type": "text",
      "pluginOptions": {
        "i18n": {
          "localized": true
        }
      }
    },
    "details": {
      "type": "string",
      "pluginOptions": {
        "i18n": {
          "localized": true
        }
      }
    },
    "bestFor": {
      "type": "string",
      "pluginOptions": {
        "i18n": {
          "localized": true
        }
      }
    },
    "features": {
      "type": "json",
      "pluginOptions": {
        "i18n": {
          "localized": true
        }
      }
    },
    "sortOrder": {
      "type": "integer",
      "pluginOptions": {
        "i18n": {
          "localized": false
        }
      }
    },
    "isDeal": {
      "type": "boolean",
      "pluginOptions": {
        "i18n": {
          "localized": false
        }
      }
    },
    "discountPrice": {
      "type": "string",
      "pluginOptions": {
        "i18n": {
          "localized": false
        }
      }
    },
    "originalPrice": {
      "type": "string",
      "pluginOptions": {
        "i18n": {
          "localized": false
        }
      }
    },
    "region": {
      "type": "string",
      "pluginOptions": {
        "i18n": {
          "localized": false
        }
      }
    },
    "coverImages": {
      "type": "media",
      "multiple": true,
      "required": false,
      "allowedTypes": [
        "images"
      ],
      "pluginOptions": {
        "i18n": {
          "localized": false
        }
      }
    }
  }
}
